stashcp/__init__.py
stashcp/opensciencegrid.org.pub
stashcp-5.6.2.data/data/share/stashcache/opensciencegrid.org.pub
stashcp-5.6.2.dist-info/LICENSE
stashcp-5.6.2.dist-info/METADATA
stashcp-5.6.2.dist-info/WHEEL
stashcp-5.6.2.dist-info/entry_points.txt
stashcp-5.6.2.dist-info/top_level.txt
stashcp-5.6.2.dist-info/RECORD
