Metadata-Version: 2.1
Name: stashcp
Version: 5.6.2
Summary: StashCache Copy
Home-page: https://github.com/opensciencegrid/StashCache
Author: Open Science Grid
Author-email: xcache@opensciencegrid.org
License: UNKNOWN
Project-URL: Bug Reports, https://github.com/opensciencegrid/StashCache/issues
Project-URL: Source, https://github.com/opensciencegrid/StashCache
Keywords: stashcache transfer
Platform: UNKNOWN
Classifier: Development Status :: 5 - Production/Stable
Classifier: Intended Audience :: Science/Research
Classifier: Topic :: Internet
Classifier: License :: OSI Approved :: Apache Software License
Classifier: Programming Language :: Python :: 2
Classifier: Programming Language :: Python :: 2.7
